LICENSE
MANIFEST.in
README.md
pyproject.toml
setup.cfg
setup.py
testpackagez/__init__.py
testpackagez/base_data.py
testpackagez/beep_utils.py
testpackagez/driver.py
testpackagez/driver_utils.py
testpackagez/exceptions.py
testpackagez/lang.py
testpackagez/local_storage_driver.py
testpackagez/opponent.py
testpackagez/profile.py
testpackagez/solve_cloudflare_captcha.py
testpackagez/tiny_profile.py
testpackagez/user_agent.py
testpackagez/window_size.py
testpackagez.egg-info/PKG-INFO
testpackagez.egg-info/SOURCES.txt
testpackagez.egg-info/dependency_links.txt
testpackagez.egg-info/requires.txt
testpackagez.egg-info/top_level.txt
testpackagez/cdp/README.md
testpackagez/cdp/__init__.py
testpackagez/cdp/accessibility.py
testpackagez/cdp/animation.py
testpackagez/cdp/audits.py
testpackagez/cdp/autofill.py
testpackagez/cdp/background_service.py
testpackagez/cdp/browser.py
testpackagez/cdp/cache_storage.py
testpackagez/cdp/cast.py
testpackagez/cdp/console.py
testpackagez/cdp/css.py
testpackagez/cdp/database.py
testpackagez/cdp/debugger.py
testpackagez/cdp/device_access.py
testpackagez/cdp/device_orientation.py
testpackagez/cdp/dom.py
testpackagez/cdp/dom_debugger.py
testpackagez/cdp/dom_snapshot.py
testpackagez/cdp/dom_storage.py
testpackagez/cdp/emulation.py
testpackagez/cdp/event_breakpoints.py
testpackagez/cdp/fed_cm.py
testpackagez/cdp/fetch.py
testpackagez/cdp/headless_experimental.py
testpackagez/cdp/heap_profiler.py
testpackagez/cdp/indexed_db.py
testpackagez/cdp/input_.py
testpackagez/cdp/inspector.py
testpackagez/cdp/io.py
testpackagez/cdp/layer_tree.py
testpackagez/cdp/log.py
testpackagez/cdp/media.py
testpackagez/cdp/memory.py
testpackagez/cdp/network.py
testpackagez/cdp/overlay.py
testpackagez/cdp/page.py
testpackagez/cdp/performance.py
testpackagez/cdp/performance_timeline.py
testpackagez/cdp/preload.py
testpackagez/cdp/profiler.py
testpackagez/cdp/py.typed
testpackagez/cdp/runtime.py
testpackagez/cdp/schema.py
testpackagez/cdp/security.py
testpackagez/cdp/service_worker.py
testpackagez/cdp/storage.py
testpackagez/cdp/system_info.py
testpackagez/cdp/target.py
testpackagez/cdp/tethering.py
testpackagez/cdp/tracing.py
