Metadata-Version: 2.1
Name: testpackagez
Version: 4.0.8
Summary: Super Fast, Super Anti-Detect, and Super Intuitive Web Driver
Author-email: Chetan <chetan@omkar.cloud>
Maintainer-email: Chetan <chetan@omkar.cloud>
License: MIT License
Project-URL: Homepage, https://github.com/omkarcloud/testpackagez
Project-URL: Bug Reports, https://github.com/omkarcloud/testpackagez/issues
Project-URL: Source, https://github.com/omkarcloud/testpackagez
Keywords: webdriver,browser,captcha,web-scraping,selenium,navigator,python3,cloudflare,anti-delect,anti-bot,bot-detection,cloudflare-bypass,distil,anti-detection
Classifier: Development Status :: 3 - Alpha
Classifier: Intended Audience :: Developers
Classifier: Topic :: Internet :: WWW/HTTP :: Browsers
Classifier: Programming Language :: Python :: 3.7
Classifier: Programming Language :: Python :: 3.8
Classifier: Programming Language :: Python :: 3.9
Classifier: Programming Language :: Python :: 3.10
Classifier: Programming Language :: Python :: 3.11
Requires-Python: >=3.5
License-File: LICENSE
Requires-Dist: websockets>=11
Requires-Dist: deprecated
Requires-Dist: botasaurus-proxy-authentication
Requires-Dist: psutil
Provides-Extra: dev
Requires-Dist: black; extra == "dev"
Requires-Dist: build; extra == "dev"
Requires-Dist: sphinx; extra == "dev"
Requires-Dist: sphinx_markdown_builder; extra == "dev"
Requires-Dist: sphinx_autodoc_typehints; extra == "dev"
Requires-Dist: furo; extra == "dev"
Requires-Dist: pygments; extra == "dev"
